Metadata-Version: 2.4
Name: img2ascii_pro
Version: 1.2
Summary: Convert images to colored ASCII art (text + HTML)
Home-page: https://github.com/MohamedElsayed-debug/img2ascii-pro
Author: Mohamed Elsayed
Author-email: ms.moh.dev@gmail.com
Project-URL: Source, https://github.com/MohamedElsayed-debug/img2ascii-pro
Classifier: Programming Language :: Python :: 3
Classifier: Operating System :: OS Independent
Classifier: License :: OSI Approved :: MIT License
License-File: LICENSE.txt
Requires-Dist: Pillow
Dynamic: author
Dynamic: author-email
Dynamic: classifier
Dynamic: description
Dynamic: description-content-type
Dynamic: home-page
Dynamic: license-file
Dynamic: project-url
Dynamic: requires-dist
Dynamic: summary
